flour-1.0.1.dist-info/METADATA
flour-1.0.1.dist-info/WHEEL
flour/__init__.py
flour/__init__.pyi
flour/py.typed
flour/flour.cpython-310-x86_64-linux-gnu.so
flour-1.0.1.dist-info/RECORD
